nepal_municipalities/__init__.py
nepal_municipalities/nepal_municipalities.py
nepal_municipalities/test.py
nepal_municipalities/data/__init__.py
nepal_municipalities/data/all_nepal_municipalities.json
nepal_municipalities/data/data.json
nepal_sub_divisions-0.0.9.dist-info/licenses/LICENSE
nepal_sub_divisions-0.0.9.dist-info/METADATA
nepal_sub_divisions-0.0.9.dist-info/WHEEL
nepal_sub_divisions-0.0.9.dist-info/top_level.txt
nepal_sub_divisions-0.0.9.dist-info/RECORD
