Metadata-Version: 2.4
Name: nepal-sub-divisions
Version: 0.0.9
Summary: Nepali  municipalities is a python package to get data about Nepali municipalities based on districts
Home-page: https://github.com/iDineshRoy/nepal-sub-divisions
Author: Dinesh Roy
Author-email: dinesh.roy@hotmail.com
License: "MIT"
Keywords: Nepali,nepal,nepal provinces,nepali districts,nepali municipalities,dinesh roy,nepali states,nepal sub divisions,nepal-sub-divisions
Classifier: Programming Language :: Python :: 3
Classifier: License :: OSI Approved :: MIT License
Classifier: Operating System :: OS Independent
Requires-Python: >=3.6
License-File: LICENSE
Dynamic: author
Dynamic: author-email
Dynamic: classifier
Dynamic: description
Dynamic: description-content-type
Dynamic: home-page
Dynamic: keywords
Dynamic: license-file
Dynamic: requires-python
Dynamic: summary
